{"url": "https://www.wikistrike.com/article-la-terre-bascule-a-180-a-intervalles-reguliers-115166692.html", "title": "La Terre pivote de 180\u00b0 \u00e0 intervalles r\u00e9guliers ", "author": "", "date": "", "content": "    L\u2019apocalypse spatiale qui touchera les quatre \u00e9l\u00e9ments, l\u2019Eau, la Terre, l\u2019Eau et l\u2019Air, menace notre plan\u00e8te, estiment les professeurs de l\u2019Universit\u00e9 de l\u2019Extr\u00eame-Orient Alexandre Panitchev et Alexandre Goulkov. La nouvelle version de la fin du monde ne laisse aucune chance de survie \u00e0 la Terre. Les experts ont expos\u00e9 leur hypoth\u00e8se dans le livre L\u2019absolu et l\u2019homme. Les scientifiques ont \u00e9tudi\u00e9 les t\u00e9moignages g\u00e9ologiques de trois catastrophes : du d\u00e9luge universel, de la p\u00e9riode glaciaire et de la mort des dinosaures. Ces trois cataclysmes dont le d\u00e9but co\u00efncidait avec un \u00e9v\u00e9nement global de courte dur\u00e9e, se sont d\u00e9roul\u00e9s conform\u00e9ment au m\u00eame sc\u00e9nario, et entra\u00eenaient finalement des extinctions de masse des esp\u00e8ces sur la plan\u00e8te. A la recherche de la nature de cet \u00e9v\u00e9nement global, les professeurs se sont rappel\u00e9s d\u2019un effet peu connu qui a \u00e9t\u00e9 d\u00e9couvert en 1985 par le cosmonaute sovi\u00e9tique Vladimir Djanibekov. Il a constat\u00e9 les modifications d'axes de rotation d'un solide en impesanteur qui pivote de 180\u00b0 \u00e0 intervalles r\u00e9guliers. Les scientifiques ont suppos\u00e9 que l\u2019effet Djanibekov pourrait jeter de la lumi\u00e8re sur les raisons des catastrophes sur la Terre qui aurait pu faire des \u00ab culbutes \u00bb similaires en impesanteur. La plan\u00e8te aurait ainsi chang\u00e9e la direction de sa rotation. Cette \u00ab inversion de l\u2019axe \u00bb aura des cons\u00e9quences irr\u00e9versibles : les for\u00eats et les sols seront soulev\u00e9s dans les en airs et retomberont, une vague \u00e9norme couvrira la plan\u00e8te, le magma sortira de la Terre et les cendres cacheront le soleil. Une nouvelle \u00e8re glaciale arrivera avec la mort de la plupart des organismes.  \u00ab Il n\u2019y a aucun doute que nous serons un jour t\u00e9moins d'\u00e9v\u00e9nements similaires \u00bb, indiquent les scientifiques. Selon leurs estimations, les cataclysmes se d\u00e9roulaient sur la plan\u00e8te tous les 23 \u00e0 30 millions d\u2019ann\u00e9es. La derni\u00e8re catastrophe s\u2019est produite il y a 25 millions d\u2019ann\u00e9es. Les professeurs supposent ainsi que la \u00ab culbute \u00bb de la Terre est attendue d\u2019un jour \u00e0 l\u2019autre. /L    "}